micropython_mma8452q/__init__.py
micropython_mma8452q/i2c_helpers.py
micropython_mma8452q/mma8452q.py
micropython_mma8452q-0.1.0.dist-info/LICENSE
micropython_mma8452q-0.1.0.dist-info/METADATA
micropython_mma8452q-0.1.0.dist-info/WHEEL
micropython_mma8452q-0.1.0.dist-info/top_level.txt
micropython_mma8452q-0.1.0.dist-info/RECORD
