Metadata-Version: 2.1
Name: micropython-mma8452q
Version: 0.1.0
Summary: MicroPython Drtiver for the NXP MMA8452Q Accelerometer
Author-email: JDM <xxyx@mailmeto.mozmail.com>
License: MIT
Project-URL: Homepage, https://github.com/jposada202020/MicroPython_MMA8452Q
Keywords: sensor,micropython,mma8452q,acceleration,accelerometer,nxp,micropython,mma8452q
Classifier: Intended Audience :: Developers
Classifier: Topic :: Software Development :: Libraries
Classifier: Topic :: Software Development :: Embedded Systems
Classifier: Topic :: System :: Hardware
Classifier: License :: OSI Approved :: MIT License
Classifier: Programming Language :: Python :: Implementation :: MicroPython
License-File: LICENSE
